amalgam/__init__.py
amalgam/api.py
diveplane_amalgam_api-2.3.12.dist-info/LICENSE.txt
diveplane_amalgam_api-2.3.12.dist-info/METADATA
diveplane_amalgam_api-2.3.12.dist-info/WHEEL
diveplane_amalgam_api-2.3.12.dist-info/top_level.txt
diveplane_amalgam_api-2.3.12.dist-info/RECORD
